<?xml version="1.0" encoding="UTF-8"?>
<!--
To change this license header, choose License Headers in Project Properties.
To change this template file, choose Tools | Templates
and open the template in the editor.
-->


<capClients 
  xmlns="http://www.witsml.org/api/140"
  xmlns:xsi="http://www.w3.org/2001/XMLSchema-instance"
  version="1.4.0">
    <capClient apiVers="1.4.1.1">
        <contact>
            <name>Geirmundur Orri Sigurdsson</name>
            <email>geirmundur.sigurdsson@nov.com</email>
            <phone>+47 47447044</phone>
        </contact>
        <description>Software engineering departent at NOV</description>
        <name>Geirmundur Orri Sigurdsson</name>
        <vendor>National Oilwell Varco</vendor>
        <version>0.0.1</version>
        <schemaVersion>1.4.1.1</schemaVersion>
    </capClient>

</capClients>
